flydev_comandos/__init__.py
flydev_comandos/drone.py
flydev_mav-0.6.0.dist-info/licenses/LICENSE
flydev_mav-0.6.0.dist-info/METADATA
flydev_mav-0.6.0.dist-info/WHEEL
flydev_mav-0.6.0.dist-info/top_level.txt
flydev_mav-0.6.0.dist-info/RECORD
